ete/__init__.py
ete/__main__.py
ete/core.py
ete/remap/__init__.py
ete/remap/yaml.py
ete-1.0.0.dist-info/entry_points.txt
ete-1.0.0.dist-info/LICENSE
ete-1.0.0.dist-info/WHEEL
ete-1.0.0.dist-info/METADATA
ete-1.0.0.dist-info/RECORD
