Metadata-Version: 2.1
Name: ete
Version: 1.0.0
Summary: Convert data types through the command line
License: Apache-2.0
Author: BD103
Author-email: dont@stalk.me
Requires-Python: >=3.8,<4.0
Classifier: License :: OSI Approved :: Apache Software License
Classifier: Programming Language :: Python :: 3
Classifier: Programming Language :: Python :: 3.8
Requires-Dist: PyYAML (>=5.4.1,<6.0.0)
Requires-Dist: click (>=8.0.0,<9.0.0)
Requires-Dist: toml (>=0.10.2,<0.11.0)
